gooderror/__init__.py
gooderror-0.0.3.dist-info/METADATA
gooderror-0.0.3.dist-info/WHEEL
gooderror-0.0.3.dist-info/top_level.txt
gooderror-0.0.3.dist-info/RECORD
