Metadata-Version: 2.1
Name: gooderror
Version: 0.0.3
Summary: GoodError is a Python library that enhances exception handling, including integration with GPT-3 for additional context.
Home-page: https://github.com/TeaByte/GoodError/
Author: 01270
Author-email: yazanemails@gmail.com
Project-URL: Source, https://github.com/TeaByte/GoodError/
Project-URL: Bug Reports, https://github.com/TeaByte/GoodError/issues
Project-URL: Documentation, https://github.com/TeaByte/GoodError/
Keywords: exception handling,GPT-3,Python library
Classifier: Development Status :: 1 - Planning
Classifier: Intended Audience :: Developers
Classifier: Programming Language :: Python :: 3
Classifier: Operating System :: Unix
Classifier: Operating System :: MacOS :: MacOS X
Classifier: Operating System :: Microsoft :: Windows
Requires-Dist: openai
